MANIFEST.in
setup.py
dzenlog_text/__init__.py
dzenlog_text/admin.py
dzenlog_text/models.py
dzenlog_text/urls.py
dzenlog_text/views.py
dzenlog_text.egg-info/PKG-INFO
dzenlog_text.egg-info/SOURCES.txt
dzenlog_text.egg-info/dependency_links.txt
dzenlog_text.egg-info/not-zip-safe
dzenlog_text.egg-info/requires.txt
dzenlog_text.egg-info/top_level.txt
dzenlog_text/migrations/0001_initial.py
dzenlog_text/migrations/__init__.py
dzenlog_text/templates/dzenlog_text/body_detail.html
dzenlog_text/templates/dzenlog_text/body_list.html
dzenlog_text/templates/dzenlog_text/detail.html
dzenlog_text/templates/dzenlog_text/list.html
