Metadata-Version: 1.0
Name: dzenlog-text
Version: 0.2.4
Summary: This is a simple application for textual blog, based on the django-dzenlog application.
Home-page: http://github.com/svetlyak40wt/django-dzenlog-text/
Author: Alexander Artemenko
Author-email: svetlyak.40wt@gmail.com
License: New BSD License
Keywords: django apps blogging dzenlog
Platform: UNKNOWN
Classifier: Development Status :: 3 - Alpha
Classifier: Environment :: Plugins
Classifier: Framework :: Django
Classifier: Intended Audience :: Developers
Classifier: License :: OSI Approved :: BSD License
Classifier: Programming Language :: Python
Classifier: Topic :: Software Development :: Libraries :: Python Modules
